odoo/addons/hr_work_entry_profile/README.rst
odoo/addons/hr_work_entry_profile/__init__.py
odoo/addons/hr_work_entry_profile/__manifest__.py
odoo/addons/hr_work_entry_profile/i18n/de.po
odoo/addons/hr_work_entry_profile/i18n/fr.po
odoo/addons/hr_work_entry_profile/i18n/hr_work_entry_profile.pot
odoo/addons/hr_work_entry_profile/i18n/it.po
odoo/addons/hr_work_entry_profile/images/screen.png
odoo/addons/hr_work_entry_profile/models/__init__.py
odoo/addons/hr_work_entry_profile/models/res_users.py
odoo/addons/hr_work_entry_profile/readme/CONTRIBUTORS.md
odoo/addons/hr_work_entry_profile/readme/CREDITS.md
odoo/addons/hr_work_entry_profile/readme/DESCRIPTION.md
odoo/addons/hr_work_entry_profile/static/description/icon.png
odoo/addons/hr_work_entry_profile/static/description/index.html
odoo/addons/hr_work_entry_profile/views/res_users.xml
odoo_addon_hr_work_entry_profile-17.0.1.0.0.3.dist-info/METADATA
odoo_addon_hr_work_entry_profile-17.0.1.0.0.3.dist-info/WHEEL
odoo_addon_hr_work_entry_profile-17.0.1.0.0.3.dist-info/top_level.txt
odoo_addon_hr_work_entry_profile-17.0.1.0.0.3.dist-info/RECORD
