Metadata-Version: 2.1
Name: odoo-addon-hr_work_entry_profile
Version: 17.0.1.0.0.3
Requires-Python: >=3.10
Requires-Dist: odoo>=17.0a,<17.1dev
Summary: User can access their work entries from the profile view.
Home-page: https://github.com/OCA/hr
License: AGPL-3
Author: Mint System GmbH, Odoo Community Association (OCA)
Author-email: support@odoo-community.org
Classifier: Programming Language :: Python
Classifier: Framework :: Odoo
Classifier: Framework :: Odoo :: 17.0
Classifier: License :: OSI Approved :: GNU Affero General Public License v3
